{"cameraMode":{"drawMode":0,"name":"Shaded","section":"Shading Mode"},"sceneLighting":true,"audioPlay":false,"sceneViewState":{"showFog":true,"showMaterialUpdate":false,"showSkybox":true,"showFlares":true,"showImageEffects":true,"showParticleSystems":true},"in2DMode":false,"pivot":{"x":0.1235806941986084,"y":-0.4005582928657532,"z":-0.4470534324645996},"rotation":{"x":-0.21464811265468598,"y":-0.3839241862297058,"z":0.09224793314933777,"w":-0.893324613571167},"size":2.088063955307007,"orthographic":false}